{
  "locations": [
    {
      "name": "CEDC Lab",
      "url": "/cedc-lab",
      "image": "img/locations/cedc_lab1.JPG",
      "tooltips": [],
      "paths": [
        {
          "label": "CEDC Loungue",
          "dest": "/cedc-lounge",
          "pos": [3034.31, -404.15, -3946.23]
        },
        {
          "label": "Tivoli Quad",
          "dest": "/tivoli-quad",
          "pos": [-2580.09, -745.37, -4210.01]
        }
      ]
    },
    {
      "name": "CEDC Lounge",
      "url": "/cedc-lounge",
      "image": "img/locations/cedc_lounge2.JPG",
      "tooltips": [],
      "paths": [
        {
          "label": "CEDC Lab",
          "dest": "/cedc-lab",
          "pos": [1478.15, -206.55, 4764.83]
        },
        {
          "label": "Speer",
          "dest": "/speer",
          "pos": [-2769.08, -289.57, 4141.84]
        },
        {
          "label": "North Lab",
          "dest": "/north-lab",
          "pos": [-2899.72, -817.49, 3988.71]
        }
      ]
    },
    {
      "name": "CIDE",
      "url": "/cide",
      "image": "img/locations/cide2.JPG",
      "tooltips": [],
      "paths": [
        {
          "label": "Spruce Parking",
          "dest": "/spruce-parking",
          "pos": [4963.80, -350.12, -428.29]
        }
      ]
    },
    {
      "name": "CMTC",
      "url": "/cmtc",
      "image": "img/locations/cmtc2.JPG",
      "tooltips": [],
      "paths": [
        {
          "label": "Tivoli Quad",
          "dest": "/tivoli-quad",
          "pos": [-4780.88, -258.09, -1410.44]
        },
        {
          "label": "Spruce Parking",
          "dest": "/spruce-parking",
          "pos": [4053.38, -240.26, -2908.84]
        }
      ]
    },
    {
      "name": "INWORKS",
      "url": "/inworks",
      "image": "img/locations/inworks2.JPG",
      "tooltips": [],
      "paths": [
        {
          "label": "Speer",
          "dest": "/speer",
          "pos": [1650.26, -62.04, 4712.30]
        },
        {
          "label": "Lawrence Street Lab",
          "dest": "/lawrence-lab",
          "pos": [-4891.57, -102.63, 1008.56]
        }
      ]
    },
    {
      "name": "Lawrence Street Labs",
      "url": "/lawrence-lab",
      "image": "img/locations/lawrence_lab1.JPG",
      "tooltips": [],
      "paths": [
        {
          "label": "Speer",
          "dest": "/speer",
          "pos": [-1371.95, -395.86, 4785.30]
        },
        {
          "label": "INWORKS",
          "dest": "/inworks",
          "pos": [-543.99, -344.61, 4955.54]
        }
      ]
    },
    {
      "name": "North Lab",
      "url": "/north-lab",
      "image": "img/locations/north_lab1.JPG",
      "tooltips": [],
      "paths": [
        {
          "label": "Speer",
          "dest": "/speer",
          "pos": [-4392.83, -1316.70, 1980.33]
        },
        {
          "label": "CEDC Lab",
          "dest": "/cedc-lab",
          "pos": [-4561.03, 399.24, 2005.90]
        },
        {
          "label": "Tivoli Quad",
          "dest": "/tivoli-quad",
          "pos": [392.40, -175.79, 4972.53]
        }
      ]
    },
    {
      "name": "Speer",
      "url": "/speer",
      "image": "img/locations/speer.JPG",
      "tooltips": [],
      "paths": [
        {
          "label": "Larence Street Lab",
          "dest": "/lawrence-lab",
          "pos": [2330.61, 351.41, 4400.96]
        },
        {
          "label": "INWORKS",
          "dest": "/inworks",
          "pos": [555.28, 305.15, 4955.32]
        },
        {
          "label": "North Labs",
          "dest": "/north-lab",
          "pos": [-3283.74, -91.00, -3761.27]
        },
        {
          "label": "CEDC Lounge",
          "dest": "/cedc-lab",
          "pos": [-3798.86, 993.44, -3078.62]
        },
        {
          "label": "Tivoli Quad",
          "dest": "/tivoli-quad",
          "pos": [-4757.09, 67.55, 1528.09]
        }
      ]
    },
    {
      "name": "Spruce Parking",
      "url": "/spruce-parking",
      "image": "img/locations/spruce_parking1.jpg",
      "tooltips": [],
      "paths": [
        {
          "label": "CIDE",
          "dest": "/cide",
          "pos": [4914.13, 108.08, 864.74]
        },
        {
          "label": "CMTC",
          "dest": "/cmtc",
          "pos": [-4995.49, 58.63, 42.14]
        }
      ]
    },
    {
      "name": "Tivoli Quad",
      "url": "/tivoli-quad",
      "image": "img/locations/tivoli_quad3.JPG",
      "tooltips": [],
      "paths": [
        {
          "label": "CMTC",
          "dest": "/cmtc",
          "pos": [-779.31, 85.52, 4928.56]
        },
        {
          "label": "Speer",
          "dest": "/speer",
          "pos": [-4053.55, 118.52, -2917.35]
        },
        {
          "label": "Spruce Parking",
          "dest": "/spruce-parking",
          "pos": [4491.08, 90.11, 2176.33]
        }
      ]
    }
  ]
}
